tjhlp_checker/__init__.py
tjhlp_checker/checker.py
tjhlp_checker/cli.py
tjhlp_checker/config.py
tjhlp_checker/libclang_patch.py
tjhlp_checker-0.1.3.dist-info/METADATA
tjhlp_checker-0.1.3.dist-info/WHEEL
tjhlp_checker-0.1.3.dist-info/entry_points.txt
tjhlp_checker-0.1.3.dist-info/RECORD
