Metadata-Version: 2.4
Name: tjhlp-checker
Version: 0.1.3
Summary: This project is a code inspection tool for teaching purposes in the "High-level Language Programming" course at Tongji University, used to check whether C/C++ code uses syntax features that violate assignment requirements.
Requires-Python: >=3.13
Requires-Dist: libclang>=18.1.1
Requires-Dist: pydantic>=2.11.1
Provides-Extra: cli
Requires-Dist: typer>=0.15.2; extra == 'cli'
